Metadata-Version: 2.1
Name: pyhttpsnippet
Version: 1.0.5
Summary: A short description of your package
Home-page: https://github.com/Mohammadwh/pyhttpsnippet/
Author: negative_boy
Author-email: negativeres@gmail.com
License: UNKNOWN
Platform: UNKNOWN
Classifier: Programming Language :: Python :: 3
Classifier: License :: OSI Approved :: MIT License
Classifier: Operating System :: OS Independent
Requires-Python: >=3.6
License-File: LICENSE
